rctaitest/__init__.py
rctaitest/__main__.py
rctaitest/aircv/__init__.py
rctaitest/aircv/aircv.py
rctaitest/aircv/cal_confidence.py
rctaitest/aircv/error.py
rctaitest/aircv/keypoint_base.py
rctaitest/aircv/keypoint_matching.py
rctaitest/aircv/keypoint_matching_contrib.py
rctaitest/aircv/multiscale_template_matching.py
rctaitest/aircv/sift.py
rctaitest/aircv/template.py
rctaitest/aircv/template_matching.py
rctaitest/aircv/utils.py
rctaitest/cli/__init__.py
rctaitest/cli/__main__.py
rctaitest/cli/info.py
rctaitest/cli/parser.py
rctaitest/cli/runner.py
rctaitest/core/__init__.py
rctaitest/core/api.py
rctaitest/core/cv.py
rctaitest/core/device.py
rctaitest/core/error.py
rctaitest/core/helper.py
rctaitest/core/settings.py
rctaitest/core/android/__init__.py
rctaitest/core/android/adb.py
rctaitest/core/android/android.py
rctaitest/core/android/constant.py
rctaitest/core/android/ime.py
rctaitest/core/android/recorder.py
rctaitest/core/android/rotation.py
rctaitest/core/android/yosemite.py
rctaitest/core/android/cap_methods/__init__.py
rctaitest/core/android/cap_methods/adbcap.py
rctaitest/core/android/cap_methods/base_cap.py
rctaitest/core/android/cap_methods/javacap.py
rctaitest/core/android/cap_methods/minicap.py
rctaitest/core/android/cap_methods/screen_proxy.py
rctaitest/core/android/static/adb/linux/adb
rctaitest/core/android/static/adb/linux_arm/adb
rctaitest/core/android/static/adb/mac/adb
rctaitest/core/android/static/adb/windows/AdbWinApi.dll
rctaitest/core/android/static/adb/windows/AdbWinUsbApi.dll
rctaitest/core/android/static/adb/windows/adb.exe
rctaitest/core/android/static/apks/Yosemite.apk
rctaitest/core/android/static/apks/maxpresent.jar
rctaitest/core/android/static/apks/rotationwatcher.jar
rctaitest/core/android/static/stf_libs/arm64-v8a/minicap
rctaitest/core/android/static/stf_libs/arm64-v8a/minicap-nopie
rctaitest/core/android/static/stf_libs/arm64-v8a/minicap.so
rctaitest/core/android/static/stf_libs/arm64-v8a/minitouch
rctaitest-1.2.0.dist-info/LICENSE
rctaitest-1.2.0.dist-info/METADATA
rctaitest-1.2.0.dist-info/WHEEL
rctaitest-1.2.0.dist-info/entry_points.txt
rctaitest-1.2.0.dist-info/top_level.txt
rctaitest-1.2.0.dist-info/RECORD
