Metadata-Version: 2.1
Name: rctaitest
Version: 1.2.0
Summary: UI Test Automation Framework for Games and Apps on Android/iOS/Windows/Linux
Home-page: https://github.com/rct-ai/rctaitest
Author: rct.ai
Author-email: shendezhou@rct.ai
License: Apache License 2.0
Keywords: automation,automated-test,game,android,ios,windows,linux
Platform: UNKNOWN
Classifier: Programming Language :: Python :: 2.7
Classifier: Programming Language :: Python :: 3.3
Classifier: Programming Language :: Python :: 3.4
Classifier: Programming Language :: Python :: 3.5
Classifier: Programming Language :: Python :: 3.6
Classifier: Programming Language :: Python :: 3.7
Classifier: Programming Language :: Python :: 3.8
Classifier: Programming Language :: Python :: 3.9
License-File: LICENSE
Requires-Dist: Jinja2 (>=2.8)
Requires-Dist: Pillow (>=3.4.0)
Requires-Dist: requests (>=2.11.1)
Requires-Dist: six
Requires-Dist: mss (==4.0.3)
Requires-Dist: numpy (<=1.19.3)
Requires-Dist: opencv-contrib-python
Requires-Dist: facebook-wda (>=1.3.3)
Requires-Dist: pywinauto (==0.6.3)
Provides-Extra: docs
Requires-Dist: sphinx ; extra == 'docs'
Requires-Dist: recommonmark ; extra == 'docs'
Requires-Dist: sphinx-rtd-theme ; extra == 'docs'
Requires-Dist: mock ; extra == 'docs'
Provides-Extra: tests
Requires-Dist: nose ; extra == 'tests'
